{
	"input": 
	{
		"filetype-comment": "type of file to load; HACC or NYX",
		"filetype": "NYX",

		"filename-comment": "name of input file",
		"filename": "../testing/data/z255_32.h5",

		"scalars-comment": "which scalars to test",
		"group" : "native_fields",
		"scalars": [ "baryon_density", "dark_matter_density", "temperature", "velocity_x", "velocity_y", "velocity_z" ],
		
		"parameters": {
			"pcnt": 50.0,
			"quant": 1.0,
			"tolerance": 1e-03
		}
  },

	"output" :
	{
		"output-decompressed" : false,
	
		"logfname-comment": "name of output log file",
		"logfname" : "runlogNYX",

		"metricsfname-comment": "name of file with output",
		"metricsfname" : "metricsNYX"
	},

	"compressor-comment" : "which compressors to test",
	"compressors" : 
	[
		{
			"name": "BigCrunch",
			"tolerance": 1E-3
		},

		{
            "name": "SZ",
            "abs" : 2E-3
        
		},

		{
			"name": "LossyWave",
			"pcnt": 50.0,
			"quant": 1.0,
			"tolerance": 1e-03
		}
	],


	"metrics-comment" : "which metrics to use",
	"metrics": [
		{
			"name" : "absolute_error"
		},

		{
			"name" : "relative_error"
		},

		{
			"name" : "mse"
		},

    {
      "name": "psnr"
    },

    {
      "name": "minmax"
    }
	]
}
